byotrack/__init__.py
byotrack/_env.py
byotrack/example_data.py
byotrack/py.typed
byotrack/utils.py
byotrack/visualize.py
byotrack/api/__init__.py
byotrack/api/features_extractor.py
byotrack/api/linker.py
byotrack/api/parameters.py
byotrack/api/refiner.py
byotrack/api/tracker.py
byotrack/api/tracks.py
byotrack/api/detector/__init__.py
byotrack/api/detector/detections.py
byotrack/api/detector/detector.py
byotrack/api/optical_flow/__init__.py
byotrack/api/optical_flow/optical_flow.py
byotrack/dataset/__init__.py
byotrack/dataset/ctc.py
byotrack/dataset/sinetra.py
byotrack/fiji/__init__.py
byotrack/fiji/io.py
byotrack/fiji/run.py
byotrack/icy/__init__.py
byotrack/icy/io.py
byotrack/icy/run.py
byotrack/implementation/__init__.py
byotrack/implementation/detector/__init__.py
byotrack/implementation/detector/refiners.py
byotrack/implementation/detector/stardist.py
byotrack/implementation/detector/wavelet.py
byotrack/implementation/linker/__init__.py
byotrack/implementation/linker/frame_by_frame/__init__.py
byotrack/implementation/linker/frame_by_frame/base.py
byotrack/implementation/linker/frame_by_frame/greedy_lap.py
byotrack/implementation/linker/frame_by_frame/kalman_linker.py
byotrack/implementation/linker/frame_by_frame/koft.py
byotrack/implementation/linker/frame_by_frame/nearest_neighbor.py
byotrack/implementation/linker/frame_by_frame/trackonstra.py
byotrack/implementation/linker/icy_emht/__init__.py
byotrack/implementation/linker/icy_emht/emht_protocol.xml
byotrack/implementation/linker/icy_emht/emht_protocol_with_full_specs.xml
byotrack/implementation/linker/icy_emht/icy_emht.py
byotrack/implementation/linker/trackmate/__init__.py
byotrack/implementation/linker/trackmate/_trackmate.py
byotrack/implementation/linker/trackmate/trackmate.py
byotrack/implementation/optical_flow/__init__.py
byotrack/implementation/optical_flow/opencv.py
byotrack/implementation/optical_flow/skimage.py
byotrack/implementation/refiner/__init__.py
byotrack-1.4.1.dist-info/licenses/LICENSE
byotrack-1.4.1.dist-info/METADATA
byotrack-1.4.1.dist-info/WHEEL
byotrack-1.4.1.dist-info/top_level.txt
byotrack-1.4.1.dist-info/RECORD
