Metadata-Version: 2.4
Name: byotrack
Version: 1.4.1
Summary: Biological particle tracking with Python
Home-page: https://github.com/raphaelreme/byotrack
Author: Raphael Reme
Author-email: raphaelreme-dev@protonmail.com
License: MIT
Keywords: Tracking,biology,machine learning,statistics,optimization
Classifier: Development Status :: 4 - Beta
Classifier: License :: OSI Approved :: MIT License
Classifier: Natural Language :: English
Classifier: Operating System :: OS Independent
Classifier: Programming Language :: Python :: 3.9
Classifier: Programming Language :: Python :: 3.10
Classifier: Programming Language :: Python :: 3.11
Classifier: Programming Language :: Python :: 3.12
Classifier: Programming Language :: Python :: 3.13
Requires-Python: >=3.9
License-File: LICENSE
Requires-Dist: backports.zstd; python_version < "3.14"
Requires-Dist: numba
Requires-Dist: numpy
Requires-Dist: opencv-python
Requires-Dist: pillow
Requires-Dist: platformdirs
Requires-Dist: pylapy[scipy]
Requires-Dist: tifffile[all]
Requires-Dist: torch
Requires-Dist: torch-tps
Requires-Dist: tqdm
Provides-Extra: full
Requires-Dist: matplotlib; extra == "full"
Requires-Dist: scikit-image; extra == "full"
Requires-Dist: stardist; python_version < "3.13" and extra == "full"
Requires-Dist: tensorflow; python_version < "3.13" and extra == "full"
Requires-Dist: torch-kf; extra == "full"
Requires-Dist: trackastra; python_version >= "3.10" and extra == "full"
Dynamic: license-file
